autotsforecast/__init__.py
autotsforecast/forecaster.py
autotsforecast/backtesting/__init__.py
autotsforecast/backtesting/validator.py
autotsforecast/features/__init__.py
autotsforecast/features/calendar.py
autotsforecast/features/engine.py
autotsforecast/hierarchical/__init__.py
autotsforecast/hierarchical/reconciliation.py
autotsforecast/interpretability/__init__.py
autotsforecast/interpretability/drivers.py
autotsforecast/models/__init__.py
autotsforecast/models/base.py
autotsforecast/models/external.py
autotsforecast/models/selection.py
autotsforecast/uncertainty/__init__.py
autotsforecast/uncertainty/intervals.py
autotsforecast/utils/__init__.py
autotsforecast/utils/data.py
autotsforecast/utils/parallel.py
autotsforecast/utils/preprocessing.py
autotsforecast/visualization/__init__.py
autotsforecast/visualization/plots.py
autotsforecast/visualization/progress.py
autotsforecast-0.3.9.dist-info/licenses/LICENSE
autotsforecast-0.3.9.dist-info/METADATA
autotsforecast-0.3.9.dist-info/WHEEL
autotsforecast-0.3.9.dist-info/top_level.txt
autotsforecast-0.3.9.dist-info/RECORD
