Metadata-Version: 2.4
Name: autotsforecast
Version: 0.3.9
Summary: Automated time series forecasting with Chronos-2 foundation model (zero-shot, no training required), per-series model selection, and interpretability.
Author-email: Weibin Xu <weibinxu86@gmail.com>
License-Expression: MIT
Project-URL: Homepage, https://github.com/weibinxu86/autotsforecast
Project-URL: Repository, https://github.com/weibinxu86/autotsforecast
Project-URL: Documentation, https://github.com/weibinxu86/autotsforecast#readme
Keywords: time series,forecasting,multivariate,automated,hierarchical,interpretability,shap,prediction intervals,conformal prediction
Classifier: Development Status :: 3 - Alpha
Classifier: Intended Audience :: Science/Research
Classifier: Topic :: Scientific/Engineering :: Artificial Intelligence
Classifier: Programming Language :: Python :: 3
Classifier: Programming Language :: Python :: 3 :: Only
Classifier: Programming Language :: Python :: 3.8
Classifier: Programming Language :: Python :: 3.9
Classifier: Programming Language :: Python :: 3.10
Classifier: Programming Language :: Python :: 3.11
Classifier: Programming Language :: Python :: 3.12
Classifier: Operating System :: OS Independent
Requires-Python: >=3.8
License-File: LICENSE
Requires-Dist: numpy>=1.21.0
Requires-Dist: pandas>=1.3.0
Requires-Dist: scikit-learn>=1.0.0
Requires-Dist: statsmodels>=0.13.0
Requires-Dist: scipy>=1.7.0
Requires-Dist: joblib>=1.1.0
Provides-Extra: viz
Requires-Dist: matplotlib>=3.4.0; extra == "viz"
Requires-Dist: seaborn>=0.11.0; extra == "viz"
Requires-Dist: plotly>=5.0.0; extra == "viz"
Provides-Extra: progress
Requires-Dist: rich>=12.0.0; extra == "progress"
Requires-Dist: tqdm>=4.60.0; extra == "progress"
Provides-Extra: interpret
Requires-Dist: shap>=0.42.0; extra == "interpret"
Provides-Extra: ml
Requires-Dist: xgboost>=2.0.0; extra == "ml"
Provides-Extra: prophet
Requires-Dist: prophet>=1.1.0; extra == "prophet"
Provides-Extra: neural
Requires-Dist: darts>=0.27.0; extra == "neural"
Requires-Dist: torch>=2.0.0; extra == "neural"
Requires-Dist: lightning>=2.0.0; extra == "neural"
Provides-Extra: chronos
Requires-Dist: chronos-forecasting>=2.2.0; extra == "chronos"
Requires-Dist: torch>=2.0.0; extra == "chronos"
Provides-Extra: holidays
Requires-Dist: holidays>=0.25; extra == "holidays"
Provides-Extra: dev
Requires-Dist: pytest>=7.0.0; extra == "dev"
Requires-Dist: pytest-cov>=3.0.0; extra == "dev"
Requires-Dist: black>=22.0.0; extra == "dev"
Requires-Dist: flake8>=4.0.0; extra == "dev"
Requires-Dist: mypy>=0.950; extra == "dev"
Requires-Dist: ipython>=8.0.0; extra == "dev"
Requires-Dist: jupyter>=1.0.0; extra == "dev"
Requires-Dist: nbformat>=5.0.0; extra == "dev"
Provides-Extra: all
Requires-Dist: matplotlib>=3.4.0; extra == "all"
Requires-Dist: seaborn>=0.11.0; extra == "all"
Requires-Dist: plotly>=5.0.0; extra == "all"
Requires-Dist: rich>=12.0.0; extra == "all"
Requires-Dist: tqdm>=4.60.0; extra == "all"
Requires-Dist: shap>=0.42.0; extra == "all"
Requires-Dist: chronos-forecasting>=2.2.0; extra == "all"
Requires-Dist: xgboost>=2.0.0; extra == "all"
Requires-Dist: prophet>=1.1.0; extra == "all"
Requires-Dist: darts>=0.27.0; extra == "all"
Requires-Dist: torch>=2.0.0; extra == "all"
Requires-Dist: lightning>=2.0.0; extra == "all"
Requires-Dist: holidays>=0.25; extra == "all"
Dynamic: license-file
